pmxt/__init__.py
pmxt/client.py
pmxt/models.py
pmxt/server_manager.py
pmxt/_server/__init__.py
pmxt/_server/bin/pmxt-ensure-server
pmxt/_server/bin/pmxt-ensure-server.js
pmxt/_server/server/bundled.js
pmxt_internal/__init__.py
pmxt_internal/api_client.py
pmxt_internal/api_response.py
pmxt_internal/configuration.py
pmxt_internal/exceptions.py
pmxt_internal/py.typed
pmxt_internal/rest.py
pmxt_internal/api/__init__.py
pmxt_internal/api/default_api.py
pmxt_internal/models/__init__.py
pmxt_internal/models/balance.py
pmxt_internal/models/base_request.py
pmxt_internal/models/base_response.py
pmxt_internal/models/cancel_order_request.py
pmxt_internal/models/create_order200_response.py
pmxt_internal/models/create_order_params.py
pmxt_internal/models/create_order_request.py
pmxt_internal/models/error_detail.py
pmxt_internal/models/error_response.py
pmxt_internal/models/exchange_credentials.py
pmxt_internal/models/exchange_credentials_signature_type.py
pmxt_internal/models/execution_price_result.py
pmxt_internal/models/fetch_balance200_response.py
pmxt_internal/models/fetch_markets200_response.py
pmxt_internal/models/fetch_markets_request.py
pmxt_internal/models/fetch_ohlcv200_response.py
pmxt_internal/models/fetch_ohlcv_request.py
pmxt_internal/models/fetch_ohlcv_request_args_inner.py
pmxt_internal/models/fetch_open_orders200_response.py
pmxt_internal/models/fetch_open_orders_request.py
pmxt_internal/models/fetch_order_book200_response.py
pmxt_internal/models/fetch_order_book_request.py
pmxt_internal/models/fetch_positions200_response.py
pmxt_internal/models/fetch_positions_request.py
pmxt_internal/models/fetch_trades200_response.py
pmxt_internal/models/fetch_trades_request.py
pmxt_internal/models/get_execution_price200_response.py
pmxt_internal/models/get_execution_price_detailed200_response.py
pmxt_internal/models/get_execution_price_request.py
pmxt_internal/models/get_execution_price_request_args_inner.py
pmxt_internal/models/get_markets_by_slug_request.py
pmxt-1.5.6.dist-info/METADATA
pmxt-1.5.6.dist-info/WHEEL
pmxt-1.5.6.dist-info/top_level.txt
pmxt-1.5.6.dist-info/RECORD
