Metadata-Version: 2.4
Name: pmxt
Version: 1.5.6
Summary: Unified prediction market data API - The ccxt for prediction markets
Author: PMXT Contributors
License: MIT
Project-URL: Homepage, https://github.com/pmxt-dev/pmxt
Project-URL: Documentation, https://github.com/pmxt-dev/pmxt#readme
Project-URL: Repository, https://github.com/pmxt-dev/pmxt
Project-URL: Issues, https://github.com/pmxt-dev/pmxt/issues
Keywords: prediction markets,polymarket,kalshi,trading,api
Classifier: Development Status :: 4 - Beta
Classifier: Intended Audience :: Developers
Classifier: License :: OSI Approved :: MIT License
Classifier: Programming Language :: Python :: 3
Classifier: Programming Language :: Python :: 3.8
Classifier: Programming Language :: Python :: 3.9
Classifier: Programming Language :: Python :: 3.10
Classifier: Programming Language :: Python :: 3.11
Classifier: Programming Language :: Python :: 3.12
Classifier: Topic :: Office/Business :: Financial
Classifier: Topic :: Software Development :: Libraries :: Python Modules
Requires-Python: >=3.8
Requires-Dist: urllib3>=1.26.0
Requires-Dist: python-dateutil>=2.8.0
Requires-Dist: pydantic>=2.0.0
Requires-Dist: typing-extensions>=4.0.0
Provides-Extra: dev
Requires-Dist: pytest>=7.0.0; extra == "dev"
Requires-Dist: pytest-asyncio>=0.21.0; extra == "dev"
Requires-Dist: black>=23.0.0; extra == "dev"
Requires-Dist: mypy>=1.0.0; extra == "dev"
